ganim/__init__.py
ganim/config.py
ganim/core.py
ganim/models.py
ganim/utils.py
ganim-0.1.0.dist-info/licenses/LICENSE
ganim-0.1.0.dist-info/METADATA
ganim-0.1.0.dist-info/WHEEL
ganim-0.1.0.dist-info/top_level.txt
ganim-0.1.0.dist-info/RECORD
