Metadata-Version: 2.4
Name: Ganim
Version: 0.1.0
Summary: Uma biblioteca Python intuitiva para treinar e usar GANs para geração de imagens.
Author-email: perepepeu <pedrohenriquerios00@gmail.com>
License-Expression: MIT
Project-URL: Homepage, https://github.com/perepepeu/Ganim
Project-URL: Bug Tracker, https://github.com/perepepeu/Ganim/issues
Classifier: Programming Language :: Python :: 3
Classifier: Operating System :: OS Independent
Classifier: Topic :: Scientific/Engineering :: Artificial Intelligence
Classifier: Topic :: Scientific/Engineering :: Image Processing
Requires-Python: >=3.8
License-File: LICENSE
Requires-Dist: torch
Requires-Dist: torchvision
Requires-Dist: numpy
Requires-Dist: matplotlib
Requires-Dist: opencv-python
Requires-Dist: tqdm
Dynamic: license-file
